ttgen/__init__.py
ttgen/combinations.py
ttgen-1.0.2.dist-info/METADATA
ttgen-1.0.2.dist-info/WHEEL
ttgen-1.0.2.dist-info/licenses/LICENCE
ttgen-1.0.2.dist-info/RECORD
