Metadata-Version: 2.3
Name: ttgen
Version: 1.0.2
Summary: Efficient algorithm for generating all unique k-combinations of a set with duplicates, based on the algorithm by Tadao Takaoka (2015, O(1) Time Generation of Adjacent Multiset Combinations)
Project-URL: Homepage, https://github.com/jajetloh/ttgen
Project-URL: Issues, https://github.com/jajetloh/ttgen/issues
Author-email: Ja-Jet Loh <jajet.codes@gmail.com>
License-File: LICENCE
Classifier: Development Status :: 5 - Production/Stable
Classifier: Intended Audience :: Developers
Classifier: Intended Audience :: Science/Research
Classifier: License :: OSI Approved :: MIT License
Classifier: Operating System :: OS Independent
Classifier: Programming Language :: Python :: 3
Requires-Python: >=3.8
Provides-Extra: dev
Requires-Dist: build; extra == 'dev'
Requires-Dist: plotly; extra == 'dev'
Requires-Dist: polars; extra == 'dev'
Requires-Dist: pytest; extra == 'dev'
